README.rst
setup.py
jw/__init__.py
jw.util.egg-info/PKG-INFO
jw.util.egg-info/SOURCES.txt
jw.util.egg-info/dependency_links.txt
jw.util.egg-info/entry_points.txt
jw.util.egg-info/namespace_packages.txt
jw.util.egg-info/requires.txt
jw.util.egg-info/top_level.txt
jw/util/__init__.py
jw/util/configuration.py
jw/util/extension.py
jw/util/file.py
jw/util/io.py
jw/util/memoize.py
jw/util/os.py
jw/util/python3hell.py
jw/util/retry.py
jw/util/split.py
jw/util/types.py
jw/util/version.py
test/test050_file.py
test/test100_configuration.py
test/test200_version.py
test/test300_python3hell.py
test/test400_os.py
test/test500_memoize.py
test/test600_types.py
test/test700_retry.py