Metadata-Version: 1.1
Name: jw.util
Version: 2.2
Summary: Version handling, YAML configuration, file renaming with various backup strategies
Home-page: https://pypi.python.org/pypi/jw.util
Author: Johnny Wezel
Author-email: dev-jay@wezel.name
License: Apache2
Keywords: utility
Platform: POSIX
Classifier: Topic :: Software Development :: Libraries :: Python Modules
Classifier: Development Status :: 5 - Production/Stable
Classifier: Intended Audience :: Developers
Classifier: License :: OSI Approved :: Apache Software License
Classifier: Natural Language :: English
Classifier: Operating System :: POSIX
Classifier: Operating System :: Unix
Classifier: Programming Language :: Python :: 2.7
Classifier: Programming Language :: Python :: 3.4
